MANIFEST.in
Makefile
README
setup.py
test/__init__.py
test/__init__.pyc
test/test_compile.py
test/test_compile.pyc
tiddlywebplugins/__init__.py
tiddlywebplugins/env.py
tiddlywebplugins.env.egg-info/PKG-INFO
tiddlywebplugins.env.egg-info/SOURCES.txt
tiddlywebplugins.env.egg-info/dependency_links.txt
tiddlywebplugins.env.egg-info/namespace_packages.txt
tiddlywebplugins.env.egg-info/not-zip-safe
tiddlywebplugins.env.egg-info/requires.txt
tiddlywebplugins.env.egg-info/top_level.txt