Metadata-Version: 1.0
Name: tiddlywebplugins.env
Version: 0.9
Summary: Simple wsgi environment debugging plugin for TiddlyWeb
Home-page: http://pypi.python.org/pypi/tiddlywebplugins.env
Author: Chris Dent
Author-email: cdent@peermore.com
License: UNKNOWN
Platform: Posix; MacOS X; Windows
